algonix/__init__.py
algonix/metrics.py
algonix/models.py
algonix/optimizers.py
algonix/utils.py
algonix-0.1.1.dist-info/METADATA
algonix-0.1.1.dist-info/WHEEL
algonix-0.1.1.dist-info/top_level.txt
algonix-0.1.1.dist-info/RECORD
