Metadata-Version: 2.4
Name: algonix
Version: 0.1.1
Summary: A simple machine learning library with custom models, optimizers, and metrics.
Home-page: https://github.com/bhushanzade02/MACHINE-LEARNING
Author: Bhushan Zade
Author-email: Bhushan Zade <bhushanzade02@gmail.com>
License: MIT
Requires-Python: >=3.6
Requires-Dist: numpy
Requires-Dist: scipy
Requires-Dist: matplotlib
Requires-Dist: scikit-learn
Dynamic: author
Dynamic: home-page
Dynamic: requires-python
